webullsdktradehk/__init__.py
webullsdktradehk/api.py
webullsdktradehk/grpc_api.py
webullsdktradehk/common/__init__.py
webullsdktradehk/common/account_type.py
webullsdktradehk/common/currency.py
webullsdktradehk/common/order_side.py
webullsdktradehk/common/order_status.py
webullsdktradehk/common/order_tif.py
webullsdktradehk/common/order_type.py
webullsdktradehk/common/trailing_type.py
webullsdktradehk/events/__init__.py
webullsdktradehk/events/types.py
webullsdktradehk/request/__init__.py
webullsdktradehk/request/cancel_order_request.py
webullsdktradehk/request/get_account_balance_request.py
webullsdktradehk/request/get_account_positions_request.py
webullsdktradehk/request/get_account_profile_request.py
webullsdktradehk/request/get_app_subscriptions.py
webullsdktradehk/request/get_open_orders_request.py
webullsdktradehk/request/get_order_detail_request.py
webullsdktradehk/request/get_today_orders_request.py
webullsdktradehk/request/palce_order_request.py
webullsdktradehk/request/replace_order_request.py
webullsdktradehk/trade/__init__.py
webullsdktradehk/trade/account_info.py
webullsdktradehk/trade/order_operation.py
webull_python_sdk_trade_hk-0.1.2.dist-info/METADATA
webull_python_sdk_trade_hk-0.1.2.dist-info/WHEEL
webull_python_sdk_trade_hk-0.1.2.dist-info/top_level.txt
webull_python_sdk_trade_hk-0.1.2.dist-info/RECORD
