Metadata-Version: 2.1
Name: webull-python-sdk-trade-hk
Version: 0.1.2
Summary: The hk trade module of Webull Python SDK.
Home-page: 
Author: Webull
Author-email: 
License: Apache License 2.0
Platform: any
Requires-Dist: webull-python-sdk-trade-events-core (==0.1.2)
Requires-Dist: webull-python-sdk-core (==0.1.2)
